cisco_documentation/VERSION
cisco_documentation/__init__.py
cisco_documentation/cisco-documentation.yaml
cisco_documentation/cli.py
cisco_documentation/config-merge.yaml
cisco_documentation/jinja-merge.yaml
cisco_documentation/port-descriptions.yaml
cisco_documentation/run-commands.yaml
cisco_documentation/ssh-creds.yaml
"cisco_documentation/templates/Customer City, ST - IP Address Listing.xlsx"
cisco_documentation/templates/creds.txt
cisco_documentation/templates/global-config.yaml
cisco_documentation/templates/jinja-config.yaml
cisco_documentation/templates/jinja.template
cisco_documentation/templates/port-descriptions.csv
cisco_documentation/templates/switch-list.txt
cisco_documentation/templates/wireshark_oui.txt
cisco_documentation-0.0.11.dist-info/LICENSE
cisco_documentation-0.0.11.dist-info/METADATA
cisco_documentation-0.0.11.dist-info/WHEEL
cisco_documentation-0.0.11.dist-info/entry_points.txt
cisco_documentation-0.0.11.dist-info/top_level.txt
cisco_documentation-0.0.11.dist-info/RECORD
