Metadata-Version: 2.1
Name: cisco-documentation
Version: 0.0.11
Summary: Gather information from switches to create documentation in excel.
Home-page: https://github.com/alphabet5/cisco_documentation
Author: John Burt
Author-email: johnburt.jab@gmail.com
Classifier: Programming Language :: Python :: 3
Classifier: License :: OSI Approved :: MIT License
Classifier: Operating System :: OS Independent
Requires-Python: >=3.9
License-File: LICENSE
Requires-Dist: napalm
Requires-Dist: yamlarg
Requires-Dist: keyring
Requires-Dist: ntc-templates
Requires-Dist: joblib
Requires-Dist: requests
Requires-Dist: openpyxl
Requires-Dist: Jinja2
Requires-Dist: rich
Requires-Dist: paramiko
